irisml/tasks/benchmark_onnx.py
irisml/tasks/predict_onnx.py
irisml_tasks_onnx-0.1.5.dist-info/LICENSE
irisml_tasks_onnx-0.1.5.dist-info/METADATA
irisml_tasks_onnx-0.1.5.dist-info/WHEEL
irisml_tasks_onnx-0.1.5.dist-info/top_level.txt
irisml_tasks_onnx-0.1.5.dist-info/RECORD
