Metadata-Version: 2.1
Name: irisml-tasks-onnx
Version: 0.1.5
Summary: ONNX-related tasks for IrisML
Author: irisdev
License: MIT
Requires-Python: >=3.8
License-File: LICENSE
Requires-Dist: irisml
Requires-Dist: irisml-tasks-training
Requires-Dist: nvidia-cublas-cu11
Requires-Dist: nvidia-cuda-runtime-cu11
Requires-Dist: nvidia-cudnn-cu11
Requires-Dist: nvidia-cufft-cu11
Requires-Dist: nvidia-curand-cu11
Requires-Dist: nvidia-nvtx-cu11
Requires-Dist: onnxruntime-gpu <1.17
